cvdastwrapper/__init__.py
cvdastwrapper/apispecs.py
cvdastwrapper/auth.py
cvdastwrapper/cv_config.yaml
cvdastwrapper/entry.py
cvdastwrapper/fuzzallspecs.py
cvdastwrapper/html_content_gen.py
cvdastwrapper/htmlreportgenerator.py
cvdastwrapper/reportcomp.py
cvdastwrapper/reportutil.py
cvdastwrapper/runall.py
cvdastwrapper/runconfig.py
cvdastwrapper/runonetest.py
cvdastwrapper/runperapi.py
cvdastwrapper/runperattack.py
cvdastwrapper/sumreport.py
cvdastwrapper/templates/index.html
cvdastwrapper/templates/assets/images/imperva_logo.png
cvdastwrapper/templates/assets/images/info-white.png
cvdastwrapper/templates/assets/images/logo_cardinal.png
cvdastwrapper/templates/assets/images/logo_navy.png
cvdastwrapper/templates/assets/images/tile-bkgnd.png
cvdastwrapper/templates/assets/images/charts/api-method-distribution-donut.png
cvdastwrapper/templates/assets/images/charts/attack-categories.png
cvdastwrapper/templates/assets/images/charts/attack-category-distribution.png
cvdastwrapper/templates/assets/images/charts/design-issues-donut.png
cvdastwrapper/templates/assets/images/charts/failedtests_info.png
cvdastwrapper/templates/assets/images/charts/filesummary_expandable.png
cvdastwrapper/templates/assets/images/charts/parameter-type-distribution-donut.png
cvdastwrapper/templates/assets/images/charts/response-code-distribution-donut.png
cvdastwrapper/templates/assets/images/charts/severity-apis.png
cvdastwrapper/templates/assets/images/charts/skippedtests.png
cvdastwrapper/templates/assets/styles/_palette.css
cvdastwrapper/templates/assets/styles/bootstrap-grid.min.css
cvdastwrapper/templates/assets/styles/chart-styles.css
cvdastwrapper/templates/assets/styles/collapsible.css
cvdastwrapper/templates/assets/styles/helper-classes--print.css
cvdastwrapper/templates/assets/styles/helper-classes.css
cvdastwrapper/templates/assets/styles/report-styles-page2.css
cvdastwrapper/templates/assets/styles/report-styles-print.css
cvdastwrapper/templates/assets/styles/report-styles.css
cvdastwrapper-1.48.25.dist-info/METADATA
cvdastwrapper-1.48.25.dist-info/WHEEL
cvdastwrapper-1.48.25.dist-info/entry_points.txt
cvdastwrapper-1.48.25.dist-info/top_level.txt
cvdastwrapper-1.48.25.dist-info/RECORD
