Metadata-Version: 2.1
Name: cvdastwrapper
Version: 1.48.25
Summary: This is a wrapper around CVDAST
Author: Bala Kumaran
Author-email: balak@cloudvector.com
License: UNKNOWN
Platform: UNKNOWN
Requires-Python: >=3.5,<4.0
Requires-Dist: cvdast
